{
  "last_updated": "2025-09-22T10:24:02.452915+00:00",
  "timezone": "Europe/Paris",
  "matches": [
    {
      "datetime": "2025-09-23T02:15:00+02:00",
      "competition": "NFL",
      "teams": "Baltimore Ravens - Detroit Lions",
      "channels": [
        {
          "name": "CH160us",
          "url": "https://envivo.govoet.my.id/160"
        },
        {
          "name": "CH88es",
          "url": "https://envivo.govoet.my.id/88"
        },
        {
          "name": "CH97es",
          "url": "https://envivo.govoet.my.id/97"
        },
        {
          "name": "CH71es",
          "url": "https://envivo.govoet.my.id/71"
        }
      ]
    }
  ]
}