{
  "last_updated": "2025-12-08T10:50:43.739808+00:00",
  "timezone": "Europe/Paris",
  "matches": [
    {
      "datetime": "2025-12-08T15:00:00+01:00",
      "competition": "Serie A",
      "teams": "Pisa - Parme",
      "channels": [
        {
          "name": "CH137it",
          "url": "https://envivo.govoet.my.id/137"
        },
        {
          "name": "CH87es",
          "url": "https://envivo.govoet.my.id/87"
        }
      ]
    },
    {
      "datetime": "2025-12-08T16:15:00+01:00",
      "competition": "Laliga 2",
      "teams": "Burgos CF - Albacete",
      "channels": [
        {
          "name": "CH53es",
          "url": "https://envivo.govoet.my.id/53"
        }
      ]
    },
    {
      "datetime": "2025-12-08T17:00:00+01:00",
      "competition": "Betfred Super League",
      "teams": "Panserraikos - Panetolikos",
      "channels": [
        {
          "name": "CH150gr",
          "url": "https://envivo.govoet.my.id/150"
        }
      ]
    },
    {
      "datetime": "2025-12-08T18:00:00+01:00",
      "competition": "Fifa Arab Cup",
      "teams": "Maroc - Arabie Saoudite",
      "channels": [
        {
          "name": "CH4fr",
          "url": "https://envivo.govoet.my.id/4"
        },
        {
          "name": "CH46ae",
          "url": "https://envivo.govoet.my.id/46"
        }
      ]
    },
    {
      "datetime": "2025-12-08T18:00:00+01:00",
      "competition": "Fifa Arab Cup",
      "teams": "Oman - Comores",
      "channels": [
        {
          "name": "CH47ae",
          "url": "https://envivo.govoet.my.id/47"
        }
      ]
    },
    {
      "datetime": "2025-12-08T18:00:00+01:00",
      "competition": "Serie A",
      "teams": "Udinese - Genoa",
      "channels": [
        {
          "name": "CH137it",
          "url": "https://envivo.govoet.my.id/137"
        },
        {
          "name": "CH98es",
          "url": "https://envivo.govoet.my.id/98"
        },
        {
          "name": "CH87es",
          "url": "https://envivo.govoet.my.id/87"
        },
        {
          "name": "CH70es",
          "url": "https://envivo.govoet.my.id/70"
        }
      ]
    },
    {
      "datetime": "2025-12-08T18:00:00+01:00",
      "competition": "Super Lig",
      "teams": "Alanyaspor - Antalyaspor",
      "channels": [
        {
          "name": "CH152tr",
          "url": "https://envivo.govoet.my.id/152"
        }
      ]
    },
    {
      "datetime": "2025-12-08T18:00:00+01:00",
      "competition": "Super Lig",
      "teams": "Besiktas - Gaziantep",
      "channels": [
        {
          "name": "CH3fr",
          "url": "https://envivo.govoet.my.id/3"
        },
        {
          "name": "CH151tr",
          "url": "https://envivo.govoet.my.id/151"
        },
        {
          "name": "CH91es",
          "url": "https://envivo.govoet.my.id/91"
        },
        {
          "name": "CH79es",
          "url": "https://envivo.govoet.my.id/79"
        },
        {
          "name": "CH69es",
          "url": "https://envivo.govoet.my.id/69"
        }
      ]
    },
    {
      "datetime": "2025-12-08T18:30:00+01:00",
      "competition": "Laliga 2",
      "teams": "Las Palmas - Mirandes",
      "channels": [
        {
          "name": "CH53es",
          "url": "https://envivo.govoet.my.id/53"
        }
      ]
    },
    {
      "datetime": "2025-12-08T20:30:00+01:00",
      "competition": "Fa Cup",
      "teams": "Brackley Town - Burton",
      "channels": [
        {
          "name": "CH126gb",
          "url": "https://envivo.govoet.my.id/126"
        }
      ]
    },
    {
      "datetime": "2025-12-08T20:30:00+01:00",
      "competition": "Laliga 2",
      "teams": "Malaga - Saragosse",
      "channels": [
        {
          "name": "CH53es",
          "url": "https://envivo.govoet.my.id/53"
        }
      ]
    },
    {
      "datetime": "2025-12-08T20:45:00+01:00",
      "competition": "Ligue 2",
      "teams": "Reims - Laval",
      "channels": [
        {
          "name": "CH2fr",
          "url": "https://envivo.govoet.my.id/2"
        }
      ]
    },
    {
      "datetime": "2025-12-08T20:45:00+01:00",
      "competition": "Serie A",
      "teams": "Torino - AC Milan",
      "channels": [
        {
          "name": "CH45fr",
          "url": "https://envivo.govoet.my.id/45"
        },
        {
          "name": "CH138it",
          "url": "https://envivo.govoet.my.id/138"
        },
        {
          "name": "CH98es",
          "url": "https://envivo.govoet.my.id/98"
        },
        {
          "name": "CH88es",
          "url": "https://envivo.govoet.my.id/88"
        },
        {
          "name": "CH70es",
          "url": "https://envivo.govoet.my.id/70"
        }
      ]
    },
    {
      "datetime": "2025-12-08T21:00:00+01:00",
      "competition": "Laliga",
      "teams": "Osasuna - Levante",
      "channels": [
        {
          "name": "CH4fr",
          "url": "https://envivo.govoet.my.id/4"
        },
        {
          "name": "CH49es",
          "url": "https://envivo.govoet.my.id/49"
        },
        {
          "name": "CH71es",
          "url": "https://envivo.govoet.my.id/71"
        },
        {
          "name": "CH94es",
          "url": "https://envivo.govoet.my.id/94"
        }
      ]
    },
    {
      "datetime": "2025-12-08T21:00:00+01:00",
      "competition": "Premier League",
      "teams": "Wolves - Manchester Utd",
      "channels": [
        {
          "name": "CH12fr",
          "url": "https://envivo.govoet.my.id/12"
        },
        {
          "name": "CH127gb",
          "url": "https://envivo.govoet.my.id/127"
        },
        {
          "name": "CH56es",
          "url": "https://envivo.govoet.my.id/56"
        },
        {
          "name": "CH120de",
          "url": "https://envivo.govoet.my.id/120"
        },
        {
          "name": "CH87es",
          "url": "https://envivo.govoet.my.id/87"
        }
      ]
    },
    {
      "datetime": "2025-12-08T21:00:00+01:00",
      "competition": "Torneo LPF",
      "teams": "Gimnasia L.P. - Estudiantes",
      "channels": [
        {
          "name": "CH75es",
          "url": "https://envivo.govoet.my.id/75"
        },
        {
          "name": "CH76es",
          "url": "https://envivo.govoet.my.id/76"
        }
      ]
    },
    {
      "datetime": "2025-12-08T21:30:00+01:00",
      "competition": "Liga Portugal",
      "teams": "Guimaraes - Gil Vicente",
      "channels": [
        {
          "name": "CH144pt",
          "url": "https://envivo.govoet.my.id/144"
        }
      ]
    },
    {
      "datetime": "2025-12-09T01:00:00+01:00",
      "competition": "Ecuador Ligapro",
      "teams": "Emelec - Macara",
      "channels": [
        {
          "name": "CH86es",
          "url": "https://envivo.govoet.my.id/86"
        }
      ]
    },
    {
      "datetime": "2025-12-09T01:00:00+01:00",
      "competition": "NBA",
      "teams": "Indiana Pacers - Sacramento Kings",
      "channels": [
        {
          "name": "CH160us",
          "url": "https://envivo.govoet.my.id/160"
        },
        {
          "name": "CH75es",
          "url": "https://envivo.govoet.my.id/75"
        }
      ]
    },
    {
      "datetime": "2025-12-09T01:30:00+01:00",
      "competition": "NBA",
      "teams": "Minnesota Timberwolves - Phoenix Suns",
      "channels": [
        {
          "name": "CH1fr",
          "url": "https://envivo.govoet.my.id/1"
        },
        {
          "name": "CH161us",
          "url": "https://envivo.govoet.my.id/161"
        },
        {
          "name": "CH98es",
          "url": "https://envivo.govoet.my.id/98"
        },
        {
          "name": "CH75es",
          "url": "https://envivo.govoet.my.id/75"
        }
      ]
    },
    {
      "datetime": "2025-12-09T01:30:00+01:00",
      "competition": "NHL",
      "teams": "Toronto Maple Leafs - Tampa Bay Lightning",
      "channels": [
        {
          "name": "CH188us",
          "url": "https://envivo.govoet.my.id/188"
        }
      ]
    },
    {
      "datetime": "2025-12-09T02:00:00+01:00",
      "competition": "NBA",
      "teams": "New Orleans Pelicans - San Antonio Spurs",
      "channels": [
        {
          "name": "CH162us",
          "url": "https://envivo.govoet.my.id/162"
        }
      ]
    },
    {
      "datetime": "2025-12-09T02:15:00+01:00",
      "competition": "NFL",
      "teams": "Los Angeles Chargers - Philadelphia Eagles",
      "channels": [
        {
          "name": "CH2fr",
          "url": "https://envivo.govoet.my.id/2"
        },
        {
          "name": "CH170us",
          "url": "https://envivo.govoet.my.id/170"
        },
        {
          "name": "CH97es",
          "url": "https://envivo.govoet.my.id/97"
        },
        {
          "name": "CH88es",
          "url": "https://envivo.govoet.my.id/88"
        }
      ]
    },
    {
      "datetime": "2025-12-09T03:00:00+01:00",
      "competition": "NHL",
      "teams": "Calgary Flames - Buffalo Sabres",
      "channels": [
        {
          "name": "CH189us",
          "url": "https://envivo.govoet.my.id/189"
        }
      ]
    },
    {
      "datetime": "2025-12-09T03:00:00+01:00",
      "competition": "NHL",
      "teams": "Utah Mammoth - Los Angeles Kings",
      "channels": [
        {
          "name": "CH190us",
          "url": "https://envivo.govoet.my.id/190"
        }
      ]
    },
    {
      "datetime": "2025-12-09T04:00:00+01:00",
      "competition": "NHL",
      "teams": "Seattle Kraken - Minnesota Wild",
      "channels": [
        {
          "name": "CH191us",
          "url": "https://envivo.govoet.my.id/191"
        }
      ]
    },
    {
      "datetime": "2025-12-09T04:00:00+01:00",
      "competition": "NHL",
      "teams": "Vancouver Canucks - Detroit Red Wings",
      "channels": [
        {
          "name": "CH192us",
          "url": "https://envivo.govoet.my.id/192"
        }
      ]
    }
  ]
}