[
  {
    "date": "29-07-2025",
    "time": "01:00",
    "iso_datetime": "2025-07-29T01:00:00+02:00",
    "competition": "Liga Betplay Dimayor",
    "teams": "Bucaramanga - Dep. Cali",
    "channels": [
      {
        "name": "CH81es",
        "url": "https://envivo.govoet.my.id/81"
      }
    ],
    "is_live": false,
    "last_updated": "2025-07-29T04:52:50.153725Z"
  },
  {
    "date": "29-07-2025",
    "time": "01:00",
    "iso_datetime": "2025-07-29T01:00:00+02:00",
    "competition": "Torneo LPF",
    "teams": "Banfield - Barracas Central",
    "channels": [
      {
        "name": "CH75es",
        "url": "https://envivo.govoet.my.id/75"
      }
    ],
    "is_live": false,
    "last_updated": "2025-07-29T04:52:50.153748Z"
  },
  {
    "date": "29-07-2025",
    "time": "03:00",
    "iso_datetime": "2025-07-29T03:00:00+02:00",
    "competition": "Liga Mx Women",
    "teams": "Santos Laguna F - Tigres F",
    "channels": [
      {
        "name": "CH155es",
        "url": "https://envivo.govoet.my.id/155"
      }
    ],
    "is_live": false,
    "last_updated": "2025-07-29T04:52:50.153758Z"
  },
  {
    "date": "29-07-2025",
    "time": "03:10",
    "iso_datetime": "2025-07-29T03:10:00+02:00",
    "competition": "Liga Betplay Dimayor",
    "teams": "Millonarios - Llaneros",
    "channels": [
      {
        "name": "CH81es",
        "url": "https://envivo.govoet.my.id/81"
      }
    ],
    "is_live": false,
    "last_updated": "2025-07-29T04:52:50.153765Z"
  },
  {
    "date": "29-07-2025",
    "time": "05:00",
    "iso_datetime": "2025-07-29T05:00:00+02:00",
    "competition": "Liga Mx Women",
    "teams": "Mazatlan FC F - Pachuca F",
    "channels": [
      {
        "name": "CH155es",
        "url": "https://envivo.govoet.my.id/155"
      }
    ],
    "is_live": false,
    "last_updated": "2025-07-29T04:52:50.153771Z"
  }
]